wandagents/__init__.py
wandagents/community.py
wandagents/eco.py
wandagents/gov.py
wandagents/network.py
wandagents/university.py
wandagents-0.0.3.dist-info/LICENSE
wandagents-0.0.3.dist-info/METADATA
wandagents-0.0.3.dist-info/WHEEL
wandagents-0.0.3.dist-info/top_level.txt
wandagents-0.0.3.dist-info/RECORD
